strip_interactive/.git/HEAD
strip_interactive/.git/config
strip_interactive/.git/description
strip_interactive/.git/hooks/applypatch-msg.sample
strip_interactive/.git/hooks/commit-msg.sample
strip_interactive/.git/hooks/fsmonitor-watchman.sample
strip_interactive/.git/hooks/post-update.sample
strip_interactive/.git/hooks/pre-applypatch.sample
strip_interactive/.git/hooks/pre-commit.sample
strip_interactive/.git/hooks/pre-push.sample
strip_interactive/.git/hooks/pre-rebase.sample
strip_interactive/.git/hooks/pre-receive.sample
strip_interactive/.git/hooks/prepare-commit-msg.sample
strip_interactive/.git/hooks/update.sample
strip_interactive/.git/info/exclude
strip_interactive/__init__.py
strip_interactive/strip_interactive.py
strip_interactive-0.1.5.dist-info/WHEEL
strip_interactive-0.1.5.dist-info/METADATA
strip_interactive-0.1.5.dist-info/RECORD
