Metadata-Version: 2.1
Name: strip-interactive
Version: 0.1.5
Summary: Strip and execute interactive Python string
Home-page: https://github.com/khuyentran1401/strip_interactive
License: Apache-2.0
Keywords: string,interactive,shell
Author: khuyentran1401
Author-email: khuyentran1476@gmail.com
Requires-Python: >=3.7.1,<4.0.0
Classifier: License :: OSI Approved :: Apache Software License
Classifier: Programming Language :: Python :: 3
Classifier: Programming Language :: Python :: 3.8
Classifier: Programming Language :: Python :: 3.9
Project-URL: Repository, https://github.com/khuyentran1401/strip_interactive
